django_div_node/__init__.py
django_div_node/div_node.py
django_div_node-0.1.1.dist-info/LICENSE
django_div_node-0.1.1.dist-info/WHEEL
django_div_node-0.1.1.dist-info/METADATA
django_div_node-0.1.1.dist-info/RECORD
