Metadata-Version: 2.1
Name: django-div-node
Version: 0.1.1
Summary: HTML custom div node in django template
Author: dev
Author-email: dev@qiyutech.tech
Requires-Python: >=3.9,<4.0
Classifier: Programming Language :: Python :: 3
Classifier: Programming Language :: Python :: 3.9
Requires-Dist: django (>=3.1,<3.2)
